beampy/__init__.py
beampy/bpm.py
beampy/examples.py
beampy/interface.py
beampy/user_interface.py
beampy/icons/application-exit.png
beampy/icons/beampy-logo.png
beampy/icons/document-open.png
beampy/icons/document-save-as.png
beampy/icons/document-save.png
beampy/icons/help-about.png
beampy/parameters/default.txt
beampy/parameters/free_propag.txt
beampy/parameters/looses.txt
beampy/parameters/losses.txt
beampy/parameters/soliton.txt
beampy-1.11.dist-info/LICENSE.rst
beampy-1.11.dist-info/METADATA
beampy-1.11.dist-info/WHEEL
beampy-1.11.dist-info/top_level.txt
beampy-1.11.dist-info/RECORD
