Metadata-Version: 2.1
Name: beampy
Version: 1.11
Summary: Beampy is a python package - with an user interface -
Home-page: https://github.com/Python-simulation/Beampy
Author: Jonathan Peltier and Marcel Soubkovsky
Author-email: jonathanp57@outlook.fr
License: MIT License
Project-URL: Documentation, https://beampy.readthedocs.io
Project-URL: Source Code, https://github.com/Python-simulation/Beampy
Platform: UNKNOWN
Classifier: Intended Audience :: Science/Research
Classifier: Programming Language :: Python
Classifier: Programming Language :: Python :: 3
Classifier: License :: OSI Approved :: MIT License
Classifier: Operating System :: OS Independent
Requires-Python: >=3.7
Requires-Dist: numpy (>=1.16)
Requires-Dist: PyQt5 (>=5.13)
Requires-Dist: matplotlib (>=3.1)
Requires-Dist: scipy (>=1.1)
Requires-Dist: numba (>=0.38)
